odoo/addons/account_invoice_import/README.rst
odoo/addons/account_invoice_import/__init__.py
odoo/addons/account_invoice_import/__manifest__.py
odoo/addons/account_invoice_import/i18n/account_invoice_import.pot
odoo/addons/account_invoice_import/i18n/de.po
odoo/addons/account_invoice_import/i18n/es.po
odoo/addons/account_invoice_import/i18n/fr.po
odoo/addons/account_invoice_import/i18n/it.po
odoo/addons/account_invoice_import/i18n/nl.po
odoo/addons/account_invoice_import/i18n/sl.po
odoo/addons/account_invoice_import/images/sshot-wizard1.png
odoo/addons/account_invoice_import/models/__init__.py
odoo/addons/account_invoice_import/models/account_invoice_import_config.py
odoo/addons/account_invoice_import/models/account_journal.py
odoo/addons/account_invoice_import/models/account_move.py
odoo/addons/account_invoice_import/models/res_company.py
odoo/addons/account_invoice_import/models/res_partner.py
odoo/addons/account_invoice_import/readme/CONFIGURE.rst
odoo/addons/account_invoice_import/readme/CONTRIBUTORS.rst
odoo/addons/account_invoice_import/readme/DESCRIPTION.rst
odoo/addons/account_invoice_import/readme/ROADMAP.rst
odoo/addons/account_invoice_import/readme/USAGE.rst
odoo/addons/account_invoice_import/scripts/inotify-sample.sh
odoo/addons/account_invoice_import/scripts/mass_invoice_import.py
odoo/addons/account_invoice_import/security/ir.model.access.csv
odoo/addons/account_invoice_import/security/rule.xml
odoo/addons/account_invoice_import/static/description/icon.png
odoo/addons/account_invoice_import/static/description/index.html
odoo/addons/account_invoice_import/tests/__init__.py
odoo/addons/account_invoice_import/tests/test_invoice_import.py
odoo/addons/account_invoice_import/tests/pdf/unknown_invoice.pdf
odoo/addons/account_invoice_import/views/account_invoice.xml
odoo/addons/account_invoice_import/views/account_invoice_import_config.xml
odoo/addons/account_invoice_import/views/account_journal_dashboard.xml
odoo14_addon_account_invoice_import-14.0.3.5.0.dist-info/METADATA
odoo14_addon_account_invoice_import-14.0.3.5.0.dist-info/WHEEL
odoo14_addon_account_invoice_import-14.0.3.5.0.dist-info/top_level.txt
odoo14_addon_account_invoice_import-14.0.3.5.0.dist-info/RECORD
